labelimg2/__init__.py
labelimg2/__main__.py
labelimg2/bg.jpg
labelimg2/bg2.jpg
labelimg2/bg3.jpg
labelimg2/bg4.jpg
labelimg2/bg5.jpg
labelimg2/bg6.jpg
labelimg2/main.py
labelimg2/status.jpg
labelimg2/data/predefined_classes.txt
labelimg2/libs/__init__.py
labelimg2/libs/canvas.py
labelimg2/libs/colorDialog.py
labelimg2/libs/combobox.py
labelimg2/libs/constants.py
labelimg2/libs/create_ml_io.py
labelimg2/libs/default_label_combobox.py
labelimg2/libs/hashableQListWidgetItem.py
labelimg2/libs/labelDialog.py
labelimg2/libs/labelFile.py
labelimg2/libs/lightWidget.py
labelimg2/libs/pascal_voc_io.py
labelimg2/libs/resources.py
labelimg2/libs/settings.py
labelimg2/libs/shape.py
labelimg2/libs/stringBundle.py
labelimg2/libs/toolBar.py
labelimg2/libs/ustr.py
labelimg2/libs/utils.py
labelimg2/libs/yolo_io.py
labelimg2/libs/zoomWidget.py
labelimg2/mixins/window.py
labelimg2/resources/icons/app.icns
labelimg2/resources/icons/app.png
labelimg2/resources/icons/app.svg
labelimg2/resources/icons/cancel.png
labelimg2/resources/icons/close.png
labelimg2/resources/icons/color.png
labelimg2/resources/icons/color_line.png
labelimg2/resources/icons/copy.png
labelimg2/resources/icons/delete.png
labelimg2/resources/icons/done.png
labelimg2/resources/icons/done.svg
labelimg2/resources/icons/edit.png
labelimg2/resources/icons/expert1.png
labelimg2/resources/icons/expert2.png
labelimg2/resources/icons/eye.png
labelimg2/resources/icons/feBlend-icon.png
labelimg2/resources/icons/file.png
labelimg2/resources/icons/fit-width.png
labelimg2/resources/icons/fit-window.png
labelimg2/resources/icons/fit.png
labelimg2/resources/icons/format_createml.png
labelimg2/resources/icons/format_voc.png
labelimg2/resources/icons/format_yolo.png
labelimg2/resources/icons/help.png
labelimg2/resources/icons/labels.png
labelimg2/resources/icons/labels.svg
labelimg2/resources/icons/light_brighten.svg
labelimg2/resources/icons/light_darken.png
labelimg2/resources/icons/light_darken.svg
labelimg2-0.0.1.dist-info/LICENSE
labelimg2-0.0.1.dist-info/METADATA
labelimg2-0.0.1.dist-info/WHEEL
labelimg2-0.0.1.dist-info/top_level.txt
labelimg2-0.0.1.dist-info/RECORD
