Metadata-Version: 2.1
Name: labelimg2
Version: 0.0.1
Summary: LabelImg v2
Author-email: yusef <yusef314159@gmail.com>
License: Copyright (c) <2015-Present> Tzutalin        
Project-URL: Homepage, https://github.com/mexusef/labelimg
Project-URL: Bug Tracker, https://github.com/mexusef/labelimg/issues
Classifier: Programming Language :: Python :: 3
Classifier: License :: OSI Approved :: MIT License
Classifier: Operating System :: OS Independent
Requires-Python: >=3.9
License-File: LICENSE
Requires-Dist: PyQt5 (~=5.15.6)
Requires-Dist: lxml (~=4.9.1)
